{
	"Id": "123",
	"attributes":[{
		"Name":"Albemarle - Temp Labor US/EMEA",
		"Owner":"Michael Sanches",
		"AccountName" : "Albemarle - USA",
		"Project_Startup_Year__c":"2016",
		"Type":"New Business",
		"airenergi__End_Date__c":"5/9/2016",
		"LeadSource":"Networking",
		"StageName":"Propose",
		"Air_Energi_VP_Location__c":"APAC",
		"airenergi__Start_Date__c":"",
		"Region__c":"South Asia",
		"TotalAnnualGP":"620,000",
		"Location__c":"Malaysia",
		"Year1__c":"20,000",
		"Account_Site__c":"Pengarang",
		"Year2__c":"300,000",
		"BUSINESS_STREAM__c":"Product Solutions",
		"Year3__c":"300,000",
		"airenergi__Project_Category__c":"Downstream Oil",
		"Basis_of_Value_Calculation__c":"Dates pushed into 2016 - management in KL delayed/nsign off on PDH terms of business, first invoice raised/ndecember 2015",
		"CreatedBy":"Darren McLean 09/09/2014 13:06",
		"LastModifiedBy":"Darren McLean 26/05/2016 2:06",
		"Description":"2015 Global bid, led by the US Global headquarters..",
		"Updated_Comments__c":"2015 Global bid, led by the US Global headquarters..",
		"Opportunity_Code__c":"01066",
		"DueDate":"9/17/2015",
		"Is_a_Bid_Response_Required__c":"Yes",
		"ContractType":"Fixed",
		"Format__c":"",
		"Type_of_Bid__c":"Global",
		"RequestReceivedDate":"9/3/2015",
		"SubmittedDate":"9/17/2015",
		"Customer_Decision_Team_Member1__c" : "Phillip Weber",
		"PSC1__c": "Global Contractor talent needs/specialization",
		"Customer_Decision_Team_Member2__c" : "Kevin LeBlanc",
		"PSC2__c": "Rates",
		"Customer_Decision_Team_Member3__c" : "Sylvain Philippe Sainton",
		"PSC3__c": "Suppplier Alignment, Rates",
		"Customer_Decision_Team_Member4__c" : "Russell Jimison",
		"PSC4__c": "Technical capabilities/Pricing"
		}],
	"Opportunity_Assessments__c" : [
		{
			"Opportunity_Assessments_Name__c" :"Albermarle 2015 Temp Labor RFP, US/EMEA-17-2015-09-03",
			"Total_Score__c":"17",
			"Discovery_Score__c":"6",
			"Relationship_Score__c":"6",
			"Positioning_Score__c":"3",
			"Differentiation_Score__c":"2",
			"Created_Date__c":"9/4/2015",
			"Created_By__c":"Michael Sanches 9/4/2015 12:15 AM"
		},
		{
			"Opportunity_Assessments_Name__c" :"Albermarle 2015 Temp Labor RFP, US/EMEA-18-2015-09-03",
			"Total_Score__c":"18",
			"Discovery_Score__c":"6",
			"Relationship_Score__c":"6",
			"Positioning_Score__c":"3",
			"Differentiation_Score__c":"2",
			"Created_Date__c":"9/4/2015",
			"Created_By__c":"Michael Sanches 9/4/2015 12:15 AM"
		}
	],
"Competitors__c":[
	{
		"Name__c":"Brunel Energy",
		"Strengths__c":"In country capability and set up, funding capacity and systems, currently holding contract with TR",
		"Weeknesses__c":"TR don't like them!"
	}
],
"ActivityHistory":[
	{
		"Subject":"Call",
		"Action":"Client Call",
		"Summary":"Hi Kelvin, I'm in town on this Wednesday..",
		"Name":"Kelvin LeBlanc",
		"DueDate":"4/25/2015",
		"AssignedTo":"Michael Sanches"
	},
	{
		"Subject":"Call",
		"Action":"Client Call",
		"Summary":"contacted looking for feedback",
		"Name":"Kelvin LeBlanc",
		"DueDate":"2/15/2016",
		"AssignedTo":"Michael Sanches"
	}
],
"NotesAndAttachments":[
	{
		"Type":"Attachment",
		"Title":"TR Signed TOB Malaysia.pdf",
		"LastModified":"11/01/2016 08:58",
		 "CreatedBy":"Darren McLean"
	},
	{
		"Type":"Attachment",
		"Title":"Madrid Presentation March 2015.pptx",
		"LastModified":"29/04/2015 12:03",
		 "CreatedBy":"Darren McLean"
	},
	{
		"Type":"Attachment",
		"Title":"TR Flowchart.pdf",
		"LastModified":"11/01/2016 08:58",
		 "CreatedBy":"Darren McLean"
	},
	{
		"Type":"Attachment",
		"Title":"TR Proposal Quota and Work Visa Support.docx",
		"LastModified":"11/01/2016 09:58",
		 "CreatedBy":"Darren McLean"
	},
	{
		"Type":"Attachment",
		"Title":"TR Project Malaysia Investor.pdf",
		"LastModified":"11/01/2016 08:58",
		 "CreatedBy":"Darren McLean"
	}
],
"OpportunityHistories" :[
	{
		"StageName":"Closed Won",
		"Probability":"100%",
		"ClosedDate":"04/12/2015",
		"LastModified":"Darren McLean, 12/01/2016 10:19"
  },
	{
		"StageName":"Closed Won",
		"Probability":"100%",
		"ClosedDate":"31/12/2015",
		"LastModified":"Darren McLean, 11/01/2016 08:41"
  },
	{
		"StageName":"Submitted",
		"Probability":"50%",
		"ClosedDate":"20/11/2015",
		"LastModified":"Raj Kumar, 16/08/2015"
  },
	{
		"StageName":"BD",
		"Probability":"5%",
		"ClosedDate":"30/06/2015",
		"LastModified":"Darren McLean, 01/07/2016 14:25"
  }
]
}
